code_tester/__init__.py
code_tester/main.py
code_tester/dependencies/__init__.py
code_tester/dependencies/dependencies.py
code_tester/dependencies/dependency.py
code_tester/genlib/__init__.py
code_tester/genlib/srbIo.py
code_tester/genlib/srb_random.py
code_tester/lib/Code_tester.py
code_tester/lib/__init__.py
code_tester/lib/args.py
code_tester/lib/comp_files.py
test/__init__.py
code_tester-0.0.7.dist-info/LICENSE
code_tester-0.0.7.dist-info/METADATA
code_tester-0.0.7.dist-info/WHEEL
code_tester-0.0.7.dist-info/entry_points.txt
code_tester-0.0.7.dist-info/top_level.txt
code_tester-0.0.7.dist-info/RECORD
