Metadata-Version: 2.1
Name: code-tester
Version: 0.0.7
Summary: A command line tool for media editing
Home-page: http://github.com/srbcheema1/code_tester
Author: Sarbjit Singh
Author-email: srbcheema1@gmail.com
License: MIT License
Platform: UNKNOWN
Classifier: Operating System :: POSIX :: Linux
Classifier: License :: OSI Approved :: MIT License
Classifier: Programming Language :: Python :: 3.5
Requires-Dist: argcomplete (==1.9.4)
Requires-Dist: srblib
